pydbconnect/PyDBConnect.py
pydbconnect/__init__.py
pydbconnect/utils.py
pydbconnect-1.0.0.dist-info/LICENSE
pydbconnect-1.0.0.dist-info/METADATA
pydbconnect-1.0.0.dist-info/WHEEL
pydbconnect-1.0.0.dist-info/top_level.txt
pydbconnect-1.0.0.dist-info/RECORD
