Metadata-Version: 2.1
Name: pydbconnect
Version: 1.0.0
Summary: A private database service library.
Home-page: UNKNOWN
Author: NexusNovelist
Author-email: <proffesionalnoice@gmail.com>
License: UNKNOWN
Keywords: python,database,server
Platform: UNKNOWN
Classifier: Development Status :: 4 - Beta
Classifier: Intended Audience :: Developers
Classifier: Programming Language :: Python :: 3
Classifier: Operating System :: Unix
Classifier: Operating System :: MacOS :: MacOS X
Classifier: Operating System :: Microsoft :: Windows
Requires-Dist: requests
